{
  "schema": 1,
  "generatedBy": "MiaHub",
  "plugins": [
    {
      "id": "miahub",
      "name": "MiaHub",
      "pluginName": "MiaHub",
      "repository": "Timefiles404/MiaHub",
      "releaseTag": "miahub-v0.2.12",
      "asset": "MiaHub-0.2.12.jar",
      "fileName": "MiaHub.jar",
      "version": "0.2.12",
      "minecraft": "1.21.x",
      "java": 21,
      "restartRequired": false,
      "dependencies": [],
      "description": "GitHub-backed manager for Mia series Paper plugins."
    },
    {
      "id": "miaforge",
      "name": "MiaForge",
      "pluginName": "MiaForge",
      "repository": "Timefiles404/MiaHub",
      "releaseTag": "miaforge-v0.2.6",
      "asset": "MiaForge-0.2.6.jar",
      "fileName": "MiaForge.jar",
      "version": "0.2.6",
      "minecraft": "1.21.x",
      "java": 21,
      "restartRequired": false,
      "dependencies": [],
      "description": "MiaForge test plugin with /miaf reload."
    },
    {
      "id": "mialimitation",
      "name": "MiaLimitation",
      "pluginName": "MiaLimitation",
      "repository": "Timefiles404/MiaHub",
      "releaseTag": "mialimitation-v1.0.0",
      "asset": "MiaLimitation-1.0.0.jar",
      "fileName": "MiaLimitation.jar",
      "version": "1.0.0",
      "minecraft": "1.21.x",
      "java": 21,
      "restartRequired": false,
      "dependencies": [],
      "passwordProtected": false,
      "description": "Item expiration management plugin with /mialimit."
    },
    {
      "id": "miapickaxe",
      "name": "MiaPickaxe",
      "pluginName": "MiaPickaxe",
      "repository": "Timefiles404/MiaHub",
      "releaseTag": "miapickaxe-v1.0.0",
      "asset": "MiaPickaxe-1.0.0.jar",
      "fileName": "MiaPickaxe.jar",
      "version": "1.0.0",
      "minecraft": "1.21.x",
      "java": 21,
      "restartRequired": false,
      "dependencies": [
        "MythicMobs"
      ],
      "passwordProtected": false,
      "description": "Upgradeable Mythic pickaxe plugin with forge GUI and optional economy hooks."
    },
    {
      "id": "miasmartgiftroll",
      "name": "MiaSmartGiftRoll",
      "pluginName": "MiaSmartGiftRoll",
      "repository": "Timefiles404/MiaHub",
      "releaseTag": "miasmartgiftroll-v1.0.0",
      "asset": "MiaSmartGiftRoll-1.0.0.jar",
      "fileName": "MiaSmartGiftRoll.jar",
      "version": "1.0.0",
      "minecraft": "1.21.x",
      "java": 21,
      "restartRequired": false,
      "dependencies": [],
      "passwordProtected": false,
      "description": "Lottery and gift distribution plugin with kit editor and player filters."
    },
    {
      "id": "miaskillpool",
      "name": "MiaSkillpool",
      "pluginName": "MiaSkillpool",
      "repository": "Timefiles404/MiaHub",
      "releaseTag": "miaskillpool-v0.2.16",
      "asset": "MiaSkillpool-0.2.16.jar",
      "fileName": "MiaSkillpool.jar",
      "version": "0.2.16",
      "minecraft": "1.21.x",
      "java": 21,
      "restartRequired": false,
      "dependencies": [
        "MythicMobs"
      ],
      "description": "MythicMobs-backed skill pool plugin with /mias."
    },
    {
      "id": "miaeco",
      "name": "MiaEco",
      "pluginName": "MiaEco",
      "repository": "Timefiles404/MiaHub",
      "releaseTag": "miaeco-v0.18.1",
      "asset": "MiaEco-0.18.1.jar",
      "fileName": "MiaEco.jar",
      "version": "0.18.1",
      "minecraft": "1.21.x",
      "java": 21,
      "restartRequired": false,
      "dependencies": [],
      "passwordProtected": false,
      "description": "Parametric procedural forest plugin: terrain-driven tree placement, async cellular tree growth, and succession."
    }
  ]
}
